circuitpython_csv.py
circuitpython_csv-2.0.2.dist-info/licenses/LICENSE-MIT
circuitpython_csv-2.0.2.dist-info/licenses/LICENSE-PSF
circuitpython_csv-2.0.2.dist-info/METADATA
circuitpython_csv-2.0.2.dist-info/WHEEL
circuitpython_csv-2.0.2.dist-info/top_level.txt
circuitpython_csv-2.0.2.dist-info/RECORD
