Metadata-Version: 2.4
Name: circuitpython-csv
Version: 2.0.2
Summary: CircuitPython helper library for working with CSV files
Author-email: Alec Delaney <tekktrik@gmail.com>
License-Expression: MIT AND PSF-2.0 AND 0BSD
Project-URL: Homepage, https://github.com/tekktrik/CircuitPython_CSV
Project-URL: Repository, https://github.com/tekktrik/CircuitPython_CSV
Project-URL: Doumentation, https://circuitpython-csv.readthedocs.io
Keywords: adafruit,csv,data,files,embedded,micropython,circuitpython
Classifier: Intended Audience :: Developers
Classifier: Topic :: Software Development :: Libraries
Classifier: Topic :: Software Development :: Embedded Systems
Classifier: Topic :: System :: Hardware
Classifier: Topic :: File Formats
Classifier: Programming Language :: Python :: 3
Classifier: Programming Language :: Python :: Implementation :: MicroPython
License-File: LICENSE-MIT
License-File: LICENSE-PSF
Requires-Dist: Adafruit-Blinka
Provides-Extra: optional
Requires-Dist: pre-commit~=4.1; extra == "optional"
Dynamic: license-file
